{"dependencies":[{"name":"./src/index.js","dynamic":true}],"generated":{"html":"<!DOCTYPE html>\n<html lang=\"en\">\n<head>\n  <meta charset=\"UTF-8\">\n  <meta name=\"viewport\" content=\"width=device-width,user-scalable=no,initial-scale=1,maximum-scale=1,minimum-scale=1\">\n  <title>parcel-vue-demo</title>\n  <!-- 引入样式 -->\n  <link rel=\"stylesheet\" href=\"https://cdn.bootcss.com/mint-ui/2.2.13/style.css\">\n\n  <script src=\"https://cdn.bootcss.com/vue/2.5.9/vue.min.js\"></script>\n  <!-- 引入组件库 -->\n  <script src=\"https://cdn.bootcss.com/mint-ui/2.2.13/index.js\"></script>\n</head>\n<body>\n  <app></app>\n  <script src=\"/dist/9bcf68a737fd04dab5101edb1b5af38d.js\"></script>\n</body>\n</html>\n"},"hash":"2ebab108d3364dff30566e59c063cb02"}